COPYING
MANIFEST.in
README
chirp.cfg
setup.cfg
setup.py
chirp/__init__.py
chirp/version.py
chirp.egg-info/PKG-INFO
chirp.egg-info/SOURCES.txt
chirp.egg-info/dependency_links.txt
chirp.egg-info/entry_points.txt
chirp.egg-info/not-zip-safe
chirp.egg-info/top_level.txt
chirp/compare/dtw.c
chirp/pitch/vitterbi.c
chirp/common/__init__.py
chirp/common/_tools.py
chirp/common/audio.py
chirp/common/clg.py
chirp/common/config.py
chirp/common/geom.py
chirp/common/graphics.py
chirp/common/math.py
chirp/common/plg.py
chirp/common/postfilter.py
chirp/common/progress.py
chirp/common/signal.py
chirp/compare/__init__.py
chirp/compare/_dtwmodule.c
chirp/compare/base_comparison.py
chirp/compare/base_storage.py
chirp/compare/ccompare.py
chirp/compare/dtw.c
chirp/compare/dtw.pyf
chirp/compare/feat_dtw.py
chirp/compare/file_storage.py
chirp/compare/pitch_dtw.py
chirp/compare/plugins.py
chirp/compare/spcc.py
chirp/compare/spec_dtw.py
chirp/compare/sqlite_storage.py
chirp/gui/BatchCompare.py
chirp/gui/BatchPitch.py
chirp/gui/BatchStats.py
chirp/gui/DrawMask.py
chirp/gui/HelpWindow.py
chirp/gui/PitchOverlayMixin.py
chirp/gui/SpecViewer.py
chirp/gui/TSViewer.py
chirp/gui/__init__.py
chirp/gui/chirpgui.py
chirp/gui/events.py
chirp/gui/wxcommon.py
chirp/gui/wxgeom.py
chirp/misc/__init__.py
chirp/misc/pitchstats.py
chirp/misc/plotpitch.py
chirp/pitch/__init__.py
chirp/pitch/_vitterbimodule.c
chirp/pitch/batch.py
chirp/pitch/particle.py
chirp/pitch/template.py
chirp/pitch/tracker.py
chirp/pitch/vitterbi.c
chirp/pitch/vitterbi.py
chirp/pitch/vitterbi.pyf
chirp/split/__init__.py
chirp/split/csplit.py
chirp/split/intervalsplit.py
examples/KENB_MZ000162_sono_1_124570_134767_m1.ebl
examples/KENB_MZ000162_sono_1_124570_134767_m1.wav
examples/KENB_MZ000162_sono_1_124570_134767_m10.ebl
examples/KENB_MZ000162_sono_1_124570_134767_m10.wav
examples/KENB_MZ000162_sono_1_124570_134767_m11.wav
examples/KENB_MZ000162_sono_1_124570_134767_m12.ebl
examples/KENB_MZ000162_sono_1_124570_134767_m12.wav
examples/KENB_MZ000162_sono_1_124570_134767_m13.ebl
examples/KENB_MZ000162_sono_1_124570_134767_m13.wav
examples/KENB_MZ000162_sono_1_124570_134767_m14.ebl
