Metadata-Version: 1.1
Name: chirp
Version: 1.2.2
Summary: Analyze and compare bioacoustic recordings
Home-page: https://dmeliza.github.io/chirp
Author: C Daniel Meliza
Author-email: "dan" at the domain "meliza.org"
License: UNKNOWN
Download-URL: https://github.com/downloads/dmeliza/chirp
Platform: UNKNOWN
Classifier: Development Status :: 5 - Production/Stable
Classifier: Intended Audience :: Science/Research
Classifier: License :: OSI Approved :: GNU General Public License (GPL)
Classifier: Programming Language :: Python
Classifier: Topic :: Scientific/Engineering
Classifier: Operating System :: Unix
Classifier: Operating System :: POSIX :: Linux
Classifier: Operating System :: MacOS :: MacOS X
Classifier: Operating System :: Microsoft :: Windows :: Windows XP
Classifier: Natural Language :: English
